{
    "50051": "scr1.sin",

    "50053": "scr3.sin",

    "50721": "btncmd.slp",
    "50729": "btntech.slp",
    "50730": "btnunit.slp",

    "53000": "dlg6_4.sin",
    "53001": "dlg6_4.slp", // This is a total guess, graphic is unused and corrupt...
    "53002": "dlg6_4d.slp",

    "53004": "btn6_4.slp",
    "53005": "btnbldg4.slp",
    "53006": "btnbrda4.slp",
    "53007": "btnbrdb4.slp",
    "53008": "btnbrdc4.slp",
    "53009": "btnoth4.slp",
    "53010": "gamea4.slp",
    "53011": "gameb4.slp",
    "53012": "gamec4.slp",
}
